Workbook

Sheet Assumptions
B1: Lumin Light — 2025-2026 Financial Model — Assumptions
B2: Every hardcoded number in this workbook lives on this tab or the Headcount tab (blue text). Everything else is a formula.
B4: REVENUE TARGETS ($)
B5: Subsidiary | C5: 2025 | D5: 2026
B6: Lumin Light USA | C6: 7850000 | D6: 9000000
B7: Lumin Light Nigeria | C7: 5100000 | D7: 6000000
B8: Total | C8: =SUM(C6:C7) -> 12950000 | D8: =SUM(D6:D7) -> 15000000
B10: COST & MARGIN ASSUMPTIONS
B11: Blended Gross Margin % (dollar-weighted across Sol 1-5 mix) | C11: 0.473
B12: Empirically calibrated from an actual generate_sales_data() run (config.RANDOM_SEED=42), not a theoretical average — see Learning Doc 2.4. If PRODUCTS or RANDOM_SEED in config.py ever change, recheck this against a fresh run's realized margin.
B14: OPERATING EXPENSE ASSUMPTIONS
B15: Benefits & Payroll Tax Loading (% of base salary) | C15: 0.25
B16: Sales Commission (% of Revenue) | C16: 0.02
B17: Annual Cost Inflation (2025 -> 2026) | C17: 0.035
B18: Annual Depreciation & Amortization — USA ($) | C18: 40000
B19: Annual Depreciation & Amortization — Nigeria ($) | C19: 20000
B21: OTHER OPERATING EXPENSE CATEGORIES — 2025 Annual Baseline ($)
B22: Category | C22: USA | D22: Nigeria | E22: Total
B23: Rent & Facilities | C23: 150000 | D23: 90000 | E23: =SUM(C23:D23) -> 240000
B24: Travel | C24: 230000 | D24: 140000 | E24: =SUM(C24:D24) -> 370000
B25: Professional Services | C25: 140000 | D25: 60000 | E25: =SUM(C25:D25) -> 200000
B26: Marketing | C26: 90000 | D26: 40000 | E26: =SUM(C26:D26) -> 130000
B27: Freight & Logistics | C27: 180000 | D27: 160000 | E27: =SUM(C27:D27) -> 340000
B28: G&A / Admin | C28: 140000 | D28: 80000 | E28: =SUM(C28:D28) -> 220000
B29: Total | C29: =SUM(C23:C28) -> 930000 | D29: =SUM(D23:D28) -> 570000 | E29: =SUM(E23:E28) -> 1500000
B31: MONTHLY REVENUE SEASONALITY INDEX (institutional year-end budget flush pushes Q4 higher) | C31: Jan | D31: Feb | E31: Mar | F31: Apr | G31: May | H31: Jun | I31: Jul | J31: Aug | K31: Sep | L31: Oct | M31: Nov | N31: Dec
C32: 0.85 | D32: 0.85 | E32: 0.9 | F32: 0.9 | G32: 0.95 | H32: 1 | I32: 0.95 | J32: 0.9 | K32: 1 | L32: 1.05 | M32: 1.3 | N32: 1.35
B33: Check (sums to 12.00 if evenly weighted; doesn't have to — formulas normalize either way) | C33: =SUM(C32:N32) -> 12
B35: AR Collection Lag (months) — institutional buyers pay slowly; matches the Python actuals model | C35: 1
B37: STARTING CASH BALANCE — Jan 1, 2025 ($)
B38: Lumin Light USA | C38: 2200000
B39: Lumin Light Nigeria | C39: 2200000

Sheet Headcount
B1: Lumin Light — Headcount & Salaries
B2: 20 roles, ~20-person operation per Tatiana. Base salaries only — Assumptions!benefits loading is applied on the P&L tabs, not here.
B4: Role | C4: Subsidiary | D4: 2025 Annual Base Salary ($) | E4: 2026 Annual Base Salary ($)
B5: CEO | C5: Lumin Light USA | D5: 240000 | E5: =D5*(1+Assumptions!$C$17) -> 248400
B6: COO | C6: Lumin Light USA | D6: 190000 | E6: =D6*(1+Assumptions!$C$17) -> 196650
B7: CFO (Fractional) | C7: Lumin Light USA | D7: 100000 | E7: =D7*(1+Assumptions!$C$17) -> 103500
B8: VP Sales | C8: Lumin Light USA | D8: 180000 | E8: =D8*(1+Assumptions!$C$17) -> 186300
B9: Regional Sales Director, West Africa | C9: Lumin Light Nigeria | D9: 115000 | E9: =D9*(1+Assumptions!$C$17) -> 119025
B10: Sales Manager, Government & Multilateral Accounts | C10: Lumin Light USA | D10: 135000 | E10: =D10*(1+Assumptions!$C$17) -> 139725
B11: Sales Manager, NGO Accounts | C11: Lumin Light USA | D11: 120000 | E11: =D11*(1+Assumptions!$C$17) -> 124200
B12: Business Development Manager | C12: Lumin Light Nigeria | D12: 75000 | E12: =D12*(1+Assumptions!$C$17) -> 77625
B13: Tender & Bid Manager | C13: Lumin Light USA | D13: 100000 | E13: =D13*(1+Assumptions!$C$17) -> 103500
B14: Supply Chain Director | C14: Lumin Light USA | D14: 155000 | E14: =D14*(1+Assumptions!$C$17) -> 160425
B15: Warehouse Manager, Houston | C15: Lumin Light USA | D15: 80000 | E15: =D15*(1+Assumptions!$C$17) -> 82800
B16: Warehouse Manager, Lagos | C16: Lumin Light Nigeria | D16: 55000 | E16: =D16*(1+Assumptions!$C$17) -> 56925
... B24: IT & Systems Administrator | C24: Lumin Light USA | D24: 90000 | E24: =D24*(1+Assumptions!$C$17) -> 93150
B26: Total Base Salary | D26: =SUM(D5:D24) -> 2122000 | E26: =SUM(E5:E24) -> 2196270
B27: Lumin Light USA Total | D27: =SUMIF(C5:C24,"Lumin Light USA",D5:D24) -> 1685000 | E27: =SUMIF(C5:C24,"Lumin Light USA",E5:E24) -> 1743975
B28: Lumin Light Nigeria Total | D28: =SUMIF(C5:C24,"Lumin Light Nigeria",D5:D24) -> 437000 | E28: =SUMIF(C5:C24,"Lumin Light Nigeria",E5:E24) -> 452295

Sheet USA PL
B1: Lumin Light USA — P&L
C2: FY2025 | P2: FY2026
C3: Annual | D3: Jan | E3: Feb | F3: Mar | G3: Apr | H3: May | I3: Jun | J3: Jul | K3: Aug | L3: Sep | M3: Oct | N3: Nov | O3: Dec | P3: Annual | Q3: Jan | R3: Feb | S3: Mar | T3: Apr | U3: May | V3: Jun | W3: Jul | X3: Aug | Y3: Sep | Z3: Oct | AA3: Nov | AB3: Dec
B6: Revenue | C6: =SUM(D6:O6) -> 7850000 | D6: =Assumptions!$C$6*Assumptions!$C$32/SUM(Assumptions!$C$32:$N$32) -> 556041.67 | E6: =Assumptions!$C$6*Assumptions!$D$32/SUM(Assumptions!$C$32:$N$32) -> 556041.67 | F6: =Assumptions!$C$6*Assumptions!$E$32/SUM(Assumptions!$C$32:$N$32) -> 588750 | G6: =Assumptions!$C$6*Assumptions!$F$32/SUM(Assumptions!$C$32:$N$32) -> 588750 | H6: =Assumptions!$C$6*Assumptions!$G$32/SUM(Assumptions!$C$32:$N$32) -> 621458.33 | I6: =Assumptions!$C$6*Assumptions!$H$32/SUM(Assumptions!$C$32:$N$32) -> 654166.67 | J6: =Assumptions!$C$6*Assumptions!$I$32/SUM(Assumptions!$C$32:$N$32) -> 621458.33 | K6: =Assumptions!$C$6*Assumptions!$J$32/SUM(Assumptions!$C$32:$N$32) -> 588750 | L6: =Assumptions!$C$6*Assumptions!$K$32/SUM(Assumptions!$C$32:$N$32) -> 654166.67 | M6: =Assumptions!$C$6*Assumptions!$L$32/SUM(Assumptions!$C$32:$N$32) -> 686875 | N6: =Assumptions!$C$6*Assumptions!$M$32/SUM(Assumptions!$C$32:$N$32) -> 850416.67 | O6: =Assumptions!$C$6*Assumptions!$N$32/SUM(Assumptions!$C$32:$N$32) -> 883125 | P6: =SUM(Q6:AB6) -> 9000000 | Q6: =Assumptions!$D$6*Assumptions!$C$32/SUM(Assumptions!$C$32:$N$32) -> 637500 | R6: =Assumptions!$D$6*Assumptions!$D$32/SUM(Assumptions!$C$32:$N$32) -> 637500 | S6: =Assumptions!$D$6*Assumptions!$E$32/SUM(Assumptions!$C$32:$N$32) -> 675000 | T6: =Assumptions!$D$6*Assumptions!$F$32/SUM(Assumptions!$C$32:$N$32) -> 675000 | U6: =Assumptions!$D$6*Assumptions!$G$32/SUM(Assumptions!$C$32:$N$32) -> 712500 | V6: =Assumptions!$D$6*Assumptions!$H$32/SUM(Assumptions!$C$32:$N$32) -> 750000 | W6: =Assumptions!$D$6*Assumptions!$I$32/SUM(Assumptions!$C$32:$N$32) -> 712500 | X6: =Assumptions!$D$6*Assumptions!$J$32/SUM(Assumptions!$C$32:$N$32) -> 675000 | Y6: =Assumptions!$D$6*Assumptions!$K$32/SUM(Assumptions!$C$32:$N$32) -> 750000 | Z6: =Assumptions!$D$6*Assumptions!$L$32/SUM(Assumptions!$C$32:$N$32) -> 787500 | AA6: =Assumptions!$D$6*Assumptions!$M$32/SUM(Assumptions!$C$32:$N$32) -> 975000 | AB6: =Assumptions!$D$6*Assumptions!$N$32/SUM(Assumptions!$C$32:$N$32) -> 1012500
B9: COGS | C9: =SUM(D9:O9) -> 4136950 | D9: =D6*(1-Assumptions!$C$11) -> 293033.96 | E9: =E6*(1-Assumptions!$C$11) -> 293033.96 | F9: =F6*(1-Assumptions!$C$11) -> 310271.25 | G9: =G6*(1-Assumptions!$C$11) -> 310271.25 | H9: =H6*(1-Assumptions!$C$11) -> 327508.54 | I9: =I6*(1-Assumptions!$C$11) -> 344745.83 | J9: =J6*(1-Assumptions!$C$11) -> 327508.54 | K9: =K6*(1-Assumptions!$C$11) -> 310271.25 | ... O9: =O6*(1-Assumptions!$C$11) -> 465406.88 | P9: =SUM(Q9:AB9) -> 4743000 | Q9: =Q6*(1-Assumptions!$C$11) -> 335962.5 | R9: =R6*(1-Assumptions!$C$11) -> 335962.5 | S9: =S6*(1-Assumptions!$C$11) -> 355725 | T9: =T6*(1-Assumptions!$C$11) -> 355725 | U9: =U6*(1-Assumptions!$C$11) -> 375487.5 | V9: =V6*(1-Assumptions!$C$11) -> 395250 | W9: =W6*(1-Assumptions!$C$11) -> 375487.5 | X9: =X6*(1-Assumptions!$C$11) -> 355725 | ... AB9: =AB6*(1-Assumptions!$C$11) -> 533587.5
B11: Gross Profit | C11: =SUM(D11:O11) -> 3713050 | D11: =D6-D9 -> 263007.71 | E11: =E6-E9 -> 263007.71 | F11: =F6-F9 -> 278478.75 | G11: =G6-G9 -> 278478.75 | H11: =H6-H9 -> 293949.79 | I11: =I6-I9 -> 309420.83 | J11: =J6-J9 -> 293949.79 | K11: =K6-K9 -> 278478.75 | ... O11: =O6-O9 -> 417718.12 | P11: =SUM(Q11:AB11) -> 4257000 | Q11: =Q6-Q9 -> 301537.5 | R11: =R6-R9 -> 301537.5 | S11: =S6-S9 -> 319275 | T11: =T6-T9 -> 319275 | U11: =U6-U9 -> 337012.5 | V11: =V6-V9 -> 354750 | W11: =W6-W9 -> 337012.5 | X11: =X6-X9 -> 319275 | ... AB11: =AB6-AB9 -> 478912.5
B12: Gross Margin % | C12: =IF(C6=0,0,C11/C6) -> 0.473 | D12: =IF(D6=0,0,D11/D6) -> 0.473 | E12: =IF(E6=0,0,E11/E6) -> 0.473 | F12: =IF(F6=0,0,F11/F6) -> 0.473 | G12: =IF(G6=0,0,G11/G6) -> 0.473 | H12: =IF(H6=0,0,H11/H6) -> 0.473 | I12: =IF(I6=0,0,I11/I6) -> 0.473 | J12: =IF(J6=0,0,J11/J6) -> 0.473 | ... AB12: =IF(AB6=0,0,AB11/AB6) -> 0.473
B14: Operating Expenses
B15: Salaries & Benefits | C15: =SUM(D15:O15) -> 2106250 | D15: =Headcount!$D$27*(1+Assumptions!$C$15)/12 -> 175520.83 | E15: =Headcount!$D$27*(1+Assumptions!$C$15)/12 -> 175520.83 | F15: =Headcount!$D$27*(1+Assumptions!$C$15)/12 -> 175520.83 | G15: =Headcount!$D$27*(1+Assumptions!$C$15)/12 -> 175520.83 | H15: =Headcount!$D$27*(1+Assumptions!$C$15)/12 -> 175520.83 | I15: =Headcount!$D$27*(1+Assumptions!$C$15)/12 -> 175520.83 | J15: =Headcount!$D$27*(1+Assumptions!$C$15)/12 -> 175520.83 | K15: =Headcount!$D$27*(1+Assumptions!$C$15)/12 -> 175520.83 | ... O15: =Headcount!$D$27*(1+Assumptions!$C$15)/12 -> 175520.83 | P15: =SUM(Q15:AB15) -> 2179968.8 | Q15: =Headcount!$E$27*(1+Assumptions!$C$15)/12 -> 181664.06 | R15: =Headcount!$E$27*(1+Assumptions!$C$15)/12 -> 181664.06 | S15: =Headcount!$E$27*(1+Assumptions!$C$15)/12 -> 181664.06 | T15: =Headcount!$E$27*(1+Assumptions!$C$15)/12 -> 181664.06 | U15: =Headcount!$E$27*(1+Assumptions!$C$15)/12 -> 181664.06 | V15: =Headcount!$E$27*(1+Assumptions!$C$15)/12 -> 181664.06 | W15: =Headcount!$E$27*(1+Assumptions!$C$15)/12 -> 181664.06 | X15: =Headcount!$E$27*(1+Assumptions!$C$15)/12 -> 181664.06 | ... AB15: =Headcount!$E$27*(1+Assumptions!$C$15)/12 -> 181664.06
B16: Sales Commission | C16: =SUM(D16:O16) -> 157000 | D16: =D6*Assumptions!$C$16 -> 11120.833 | E16: =E6*Assumptions!$C$16 -> 11120.833 | F16: =F6*Assumptions!$C$16 -> 11775 | G16: =G6*Assumptions!$C$16 -> 11775 | H16: =H6*Assumptions!$C$16 -> 12429.167 | I16: =I6*Assumptions!$C$16 -> 13083.333 | J16: =J6*Assumptions!$C$16 -> 12429.167 | K16: =K6*Assumptions!$C$16 -> 11775 | ... O16: =O6*Assumptions!$C$16 -> 17662.5 | P16: =SUM(Q16:AB16) -> 180000 | Q16: =Q6*Assumptions!$C$16 -> 12750 | R16: =R6*Assumptions!$C$16 -> 12750 | S16: =S6*Assumptions!$C$16 -> 13500 | T16: =T6*Assumptions!$C$16 -> 13500 | U16: =U6*Assumptions!$C$16 -> 14250 | V16: =V6*Assumptions!$C$16 -> 15000 | W16: =W6*Assumptions!$C$16 -> 14250 | X16: =X6*Assumptions!$C$16 -> 13500 | ... AB16: =AB6*Assumptions!$C$16 -> 20250
B17: Rent & Facilities | C17: =SUM(D17:O17) -> 150000 | D17: =Assumptions!$C$23/12 -> 12500 | E17: =Assumptions!$C$23/12 -> 12500 | F17: =Assumptions!$C$23/12 -> 12500 | G17: =Assumptions!$C$23/12 -> 12500 | H17: =Assumptions!$C$23/12 -> 12500 | I17: =Assumptions!$C$23/12 -> 12500 | J17: =Assumptions!$C$23/12 -> 12500 | K17: =Assumptions!$C$23/12 -> 12500 | ... O17: =Assumptions!$C$23/12 -> 12500 | P17: =SUM(Q17:AB17) -> 155250 | Q17: =Assumptions!$C$23*(1+Assumptions!$C$17)/12 -> 12937.5 | R17: =Assumptions!$C$23*(1+Assumptions!$C$17)/12 -> 12937.5 | S17: =Assumptions!$C$23*(1+Assumptions!$C$17)/12 -> 12937.5 | T17: =Assumptions!$C$23*(1+Assumptions!$C$17)/12 -> 12937.5 | U17: =Assumptions!$C$23*(1+Assumptions!$C$17)/12 -> 12937.5 | V17: =Assumptions!$C$23*(1+Assumptions!$C$17)/12 -> 12937.5 | W17: =Assumptions!$C$23*(1+Assumptions!$C$17)/12 -> 12937.5 | X17: =Assumptions!$C$23*(1+Assumptions!$C$17)/12 -> 12937.5 | ... AB17: =Assumptions!$C$23*(1+Assumptions!$C$17)/12 -> 12937.5
B18: Travel | C18: =SUM(D18:O18) -> 230000 | D18: =Assumptions!$C$24/12 -> 19166.667 | E18: =Assumptions!$C$24/12 -> 19166.667 | F18: =Assumptions!$C$24/12 -> 19166.667 | G18: =Assumptions!$C$24/12 -> 19166.667 | H18: =Assumptions!$C$24/12 -> 19166.667 | I18: =Assumptions!$C$24/12 -> 19166.667 | J18: =Assumptions!$C$24/12 -> 19166.667 | K18: =Assumptions!$C$24/12 -> 19166.667 | ... O18: =Assumptions!$C$24/12 -> 19166.667 | P18: =SUM(Q18:AB18) -> 238050 | Q18: =Assumptions!$C$24*(1+Assumptions!$C$17)/12 -> 19837.5 | R18: =Assumptions!$C$24*(1+Assumptions!$C$17)/12 -> 19837.5 | S18: =Assumptions!$C$24*(1+Assumptions!$C$17)/12 -> 19837.5 | T18: =Assumptions!$C$24*(1+Assumptions!$C$17)/12 -> 19837.5 | U18: =Assumptions!$C$24*(1+Assumptions!$C$17)/12 -> 19837.5 | V18: =Assumptions!$C$24*(1+Assumptions!$C$17)/12 -> 19837.5 | W18: =Assumptions!$C$24*(1+Assumptions!$C$17)/12 -> 19837.5 | X18: =Assumptions!$C$24*(1+Assumptions!$C$17)/12 -> 19837.5 | ... AB18: =Assumptions!$C$24*(1+Assumptions!$C$17)/12 -> 19837.5
B19: Professional Services | C19: =SUM(D19:O19) -> 140000 | D19: =Assumptions!$C$25/12 -> 11666.667 | E19: =Assumptions!$C$25/12 -> 11666.667 | F19: =Assumptions!$C$25/12 -> 11666.667 | G19: =Assumptions!$C$25/12 -> 11666.667 | H19: =Assumptions!$C$25/12 -> 11666.667 | I19: =Assumptions!$C$25/12 -> 11666.667 | J19: =Assumptions!$C$25/12 -> 11666.667 | K19: =Assumptions!$C$25/12 -> 11666.667 | ... O19: =Assumptions!$C$25/12 -> 11666.667 | P19: =SUM(Q19:AB19) -> 144900 | Q19: =Assumptions!$C$25*(1+Assumptions!$C$17)/12 -> 12075 | R19: =Assumptions!$C$25*(1+Assumptions!$C$17)/12 -> 12075 | S19: =Assumptions!$C$25*(1+Assumptions!$C$17)/12 -> 12075 | T19: =Assumptions!$C$25*(1+Assumptions!$C$17)/12 -> 12075 | U19: =Assumptions!$C$25*(1+Assumptions!$C$17)/12 -> 12075 | V19: =Assumptions!$C$25*(1+Assumptions!$C$17)/12 -> 12075 | W19: =Assumptions!$C$25*(1+Assumptions!$C$17)/12 -> 12075 | X19: =Assumptions!$C$25*(1+Assumptions!$C$17)/12 -> 12075 | ... AB19: =Assumptions!$C$25*(1+Assumptions!$C$17)/12 -> 12075
B20: Marketing | C20: =SUM(D20:O20) -> 90000 | D20: =Assumptions!$C$26/12 -> 7500 | E20: =Assumptions!$C$26/12 -> 7500 | F20: =Assumptions!$C$26/12 -> 7500 | G20: =Assumptions!$C$26/12 -> 7500 | H20: =Assumptions!$C$26/12 -> 7500 | I20: =Assumptions!$C$26/12 -> 7500 | J20: =Assumptions!$C$26/12 -> 7500 | K20: =Assumptions!$C$26/12 -> 7500 | ... O20: =Assumptions!$C$26/12 -> 7500 | P20: =SUM(Q20:AB20) -> 93150 | Q20: =Assumptions!$C$26*(1+Assumptions!$C$17)/12 -> 7762.5 | R20: =Assumptions!$C$26*(1+Assumptions!$C$17)/12 -> 7762.5 | S20: =Assumptions!$C$26*(1+Assumptions!$C$17)/12 -> 7762.5 | T20: =Assumptions!$C$26*(1+Assumptions!$C$17)/12 -> 7762.5 | U20: =Assumptions!$C$26*(1+Assumptions!$C$17)/12 -> 7762.5 | V20: =Assumptions!$C$26*(1+Assumptions!$C$17)/12 -> 7762.5 | W20: =Assumptions!$C$26*(1+Assumptions!$C$17)/12 -> 7762.5 | X20: =Assumptions!$C$26*(1+Assumptions!$C$17)/12 -> 7762.5 | ... AB20: =Assumptions!$C$26*(1+Assumptions!$C$17)/12 -> 7762.5
B21: Freight & Logistics | C21: =SUM(D21:O21) -> 180000 | D21: =Assumptions!$C$27/12 -> 15000 | E21: =Assumptions!$C$27/12 -> 15000 | F21: =Assumptions!$C$27/12 -> 15000 | G21: =Assumptions!$C$27/12 -> 15000 | H21: =Assumptions!$C$27/12 -> 15000 | I21: =Assumptions!$C$27/12 -> 15000 | J21: =Assumptions!$C$27/12 -> 15000 | K21: =Assumptions!$C$27/12 -> 15000 | ... O21: =Assumptions!$C$27/12 -> 15000 | P21: =SUM(Q21:AB21) -> 186300 | Q21: =Assumptions!$C$27*(1+Assumptions!$C$17)/12 -> 15525 | R21: =Assumptions!$C$27*(1+Assumptions!$C$17)/12 -> 15525 | S21: =Assumptions!$C$27*(1+Assumptions!$C$17)/12 -> 15525 | T21: =Assumptions!$C$27*(1+Assumptions!$C$17)/12 -> 15525 | U21: =Assumptions!$C$27*(1+Assumptions!$C$17)/12 -> 15525 | V21: =Assumptions!$C$27*(1+Assumptions!$C$17)/12 -> 15525 | W21: =Assumptions!$C$27*(1+Assumptions!$C$17)/12 -> 15525 | X21: =Assumptions!$C$27*(1+Assumptions!$C$17)/12 -> 15525 | ... AB21: =Assumptions!$C$27*(1+Assumptions!$C$17)/12 -> 15525
B22: G&A / Admin | C22: =SUM(D22:O22) -> 140000 | D22: =Assumptions!$C$28/12 -> 11666.667 | E22: =Assumptions!$C$28/12 -> 11666.667 | F22: =Assumptions!$C$28/12 -> 11666.667 | G22: =Assumptions!$C$28/12 -> 11666.667 | H22: =Assumptions!$C$28/12 -> 11666.667 | I22: =Assumptions!$C$28/12 -> 11666.667 | J22: =Assumptions!$C$28/12 -> 11666.667 | K22: =Assumptions!$C$28/12 -> 11666.667 | ... O22: =Assumptions!$C$28/12 -> 11666.667 | P22: =SUM(Q22:AB22) -> 144900 | Q22: =Assumptions!$C$28*(1+Assumptions!$C$17)/12 -> 12075 | R22: =Assumptions!$C$28*(1+Assumptions!$C$17)/12 -> 12075 | S22: =Assumptions!$C$28*(1+Assumptions!$C$17)/12 -> 12075 | T22: =Assumptions!$C$28*(1+Assumptions!$C$17)/12 -> 12075 | U22: =Assumptions!$C$28*(1+Assumptions!$C$17)/12 -> 12075 | V22: =Assumptions!$C$28*(1+Assumptions!$C$17)/12 -> 12075 | W22: =Assumptions!$C$28*(1+Assumptions!$C$17)/12 -> 12075 | X22: =Assumptions!$C$28*(1+Assumptions!$C$17)/12 -> 12075 | ... AB22: =Assumptions!$C$28*(1+Assumptions!$C$17)/12 -> 12075
B23: Total Operating Expenses | C23: =SUM(D23:O23) -> 3193250 | D23: =SUM(D15:D22) -> 264141.67 | E23: =SUM(E15:E22) -> 264141.67 | F23: =SUM(F15:F22) -> 264795.83 | G23: =SUM(G15:G22) -> 264795.83 | H23: =SUM(H15:H22) -> 265450 | I23: =SUM(I15:I22) -> 266104.17 | J23: =SUM(J15:J22) -> 265450 | K23: =SUM(K15:K22) -> 264795.83 | ... O23: =SUM(O15:O22) -> 270683.33 | P23: =SUM(Q23:AB23) -> 3322518.8 | Q23: =SUM(Q15:Q22) -> 274626.56 | R23: =SUM(R15:R22) -> 274626.56 | S23: =SUM(S15:S22) -> 275376.56 | T23: =SUM(T15:T22) -> 275376.56 | U23: =SUM(U15:U22) -> 276126.56 | V23: =SUM(V15:V22) -> 276876.56 | W23: =SUM(W15:W22) -> 276126.56 | X23: =SUM(X15:X22) -> 275376.56 | ... AB23: =SUM(AB15:AB22) -> 282126.56
B25: EBITDA | C25: =SUM(D25:O25) -> 519800 | D25: =D11-D23 -> -1133.9583 | E25: =E11-E23 -> -1133.9583 | F25: =F11-F23 -> 13682.917 | G25: =G11-G23 -> 13682.917 | H25: =H11-H23 -> 28499.792 | I25: =I11-I23 -> 43316.667 | J25: =J11-J23 -> 28499.792 | K25: =K11-K23 -> 13682.917 | ... O25: =O11-O23 -> 147034.79 | P25: =SUM(Q25:AB25) -> 934481.25 | Q25: =Q11-Q23 -> 26910.938 | R25: =R11-R23 -> 26910.938 | S25: =S11-S23 -> 43898.438 | T25: =T11-T23 -> 43898.438 | U25: =U11-U23 -> 60885.938 | V25: =V11-V23 -> 77873.438 | W25: =W11-W23 -> 60885.938 | X25: =X11-X23 -> 43898.438 | ... AB25: =AB11-AB23 -> 196785.94
B26: EBITDA Margin % | C26: =IF(C6=0,0,C25/C6) -> 0.066216561 | D26: =IF(D6=0,0,D25/D6) -> -0.0020393406 | E26: =IF(E6=0,0,E25/E6) -> -0.0020393406 | F26: =IF(F6=0,0,F25/F6) -> 0.023240623 | G26: =IF(G6=0,0,G25/G6) -> 0.023240623 | H26: =IF(H6=0,0,H25/H6) -> 0.045859537 | I26: =IF(I6=0,0,I25/I6) -> 0.066216561 | J26: =IF(J6=0,0,J25/J6) -> 0.045859537 | ... AB26: =IF(AB6=0,0,AB25/AB6) -> 0.19435648
B28: Depreciation & Amortization | C28: =SUM(D28:O28) -> 40000 | D28: =Assumptions!$C$18/12 -> 3333.3333 | E28: =Assumptions!$C$18/12 -> 3333.3333 | F28: =Assumptions!$C$18/12 -> 3333.3333 | G28: =Assumptions!$C$18/12 -> 3333.3333 | H28: =Assumptions!$C$18/12 -> 3333.3333 | I28: =Assumptions!$C$18/12 -> 3333.3333 | J28: =Assumptions!$C$18/12 -> 3333.3333 | K28: =Assumptions!$C$18/12 -> 3333.3333 | ... O28: =Assumptions!$C$18/12 -> 3333.3333 | P28: =SUM(Q28:AB28) -> 40000 | Q28: =Assumptions!$C$18/12 -> 3333.3333 | R28: =Assumptions!$C$18/12 -> 3333.3333 | S28: =Assumptions!$C$18/12 -> 3333.3333 | T28: =Assumptions!$C$18/12 -> 3333.3333 | U28: =Assumptions!$C$18/12 -> 3333.3333 | V28: =Assumptions!$C$18/12 -> 3333.3333 | W28: =Assumptions!$C$18/12 -> 3333.3333 | X28: =Assumptions!$C$18/12 -> 3333.3333 | ... AB28: =Assumptions!$C$18/12 -> 3333.3333
B30: EBIT | C30: =SUM(D30:O30) -> 479800 | D30: =D25-D28 -> -4467.2917 | E30: =E25-E28 -> -4467.2917 | F30: =F25-F28 -> 10349.583 | G30: =G25-G28 -> 10349.583 | H30: =H25-H28 -> 25166.458 | I30: =I25-I28 -> 39983.333 | J30: =J25-J28 -> 25166.458 | K30: =K25-K28 -> 10349.583 | ... O30: =O25-O28 -> 143701.46 | P30: =SUM(Q30:AB30) -> 894481.25 | Q30: =Q25-Q28 -> 23577.604 | R30: =R25-R28 -> 23577.604 | S30: =S25-S28 -> 40565.104 | T30: =T25-T28 -> 40565.104 | U30: =U25-U28 -> 57552.604 | V30: =V25-V28 -> 74540.104 | W30: =W25-W28 -> 57552.604 | X30: =X25-X28 -> 40565.104 | ... AB30: =AB25-AB28 -> 193452.6
B31: EBIT Margin % | C31: =IF(C6=0,0,C30/C6) -> 0.061121019 | D31: =IF(D6=0,0,D30/D6) -> -0.0080340952 | E31: =IF(E6=0,0,E30/E6) -> -0.0080340952 | F31: =IF(F6=0,0,F30/F6) -> 0.01757891 | G31: =IF(G6=0,0,G30/G6) -> 0.01757891 | H31: =IF(H6=0,0,H30/H6) -> 0.04049581 | I31: =IF(I6=0,0,I30/I6) -> 0.061121019 | J31: =IF(J6=0,0,J30/J6) -> 0.04049581 | ... AB31: =IF(AB6=0,0,AB30/AB6) -> 0.1910643

Sheet Nigeria PL
B1: Lumin Light Nigeria — P&L
C2: FY2025 | P2: FY2026
C3: Annual | D3: Jan | E3: Feb | F3: Mar | G3: Apr | H3: May | I3: Jun | J3: Jul | K3: Aug | L3: Sep | M3: Oct | N3: Nov | O3: Dec | P3: Annual | Q3: Jan | R3: Feb | S3: Mar | T3: Apr | U3: May | V3: Jun | W3: Jul | X3: Aug | Y3: Sep | Z3: Oct | AA3: Nov | AB3: Dec
B6: Revenue | C6: =SUM(D6:O6) -> 5100000 | D6: =Assumptions!$C$7*Assumptions!$C$32/SUM(Assumptions!$C$32:$N$32) -> 361250 | E6: =Assumptions!$C$7*Assumptions!$D$32/SUM(Assumptions!$C$32:$N$32) -> 361250 | F6: =Assumptions!$C$7*Assumptions!$E$32/SUM(Assumptions!$C$32:$N$32) -> 382500 | G6: =Assumptions!$C$7*Assumptions!$F$32/SUM(Assumptions!$C$32:$N$32) -> 382500 | H6: =Assumptions!$C$7*Assumptions!$G$32/SUM(Assumptions!$C$32:$N$32) -> 403750 | I6: =Assumptions!$C$7*Assumptions!$H$32/SUM(Assumptions!$C$32:$N$32) -> 425000 | J6: =Assumptions!$C$7*Assumptions!$I$32/SUM(Assumptions!$C$32:$N$32) -> 403750 | K6: =Assumptions!$C$7*Assumptions!$J$32/SUM(Assumptions!$C$32:$N$32) -> 382500 | L6: =Assumptions!$C$7*Assumptions!$K$32/SUM(Assumptions!$C$32:$N$32) -> 425000 | M6: =Assumptions!$C$7*Assumptions!$L$32/SUM(Assumptions!$C$32:$N$32) -> 446250 | N6: =Assumptions!$C$7*Assumptions!$M$32/SUM(Assumptions!$C$32:$N$32) -> 552500 | O6: =Assumptions!$C$7*Assumptions!$N$32/SUM(Assumptions!$C$32:$N$32) -> 573750 | P6: =SUM(Q6:AB6) -> 6000000 | Q6: =Assumptions!$D$7*Assumptions!$C$32/SUM(Assumptions!$C$32:$N$32) -> 425000 | R6: =Assumptions!$D$7*Assumptions!$D$32/SUM(Assumptions!$C$32:$N$32) -> 425000 | S6: =Assumptions!$D$7*Assumptions!$E$32/SUM(Assumptions!$C$32:$N$32) -> 450000 | T6: =Assumptions!$D$7*Assumptions!$F$32/SUM(Assumptions!$C$32:$N$32) -> 450000 | U6: =Assumptions!$D$7*Assumptions!$G$32/SUM(Assumptions!$C$32:$N$32) -> 475000 | V6: =Assumptions!$D$7*Assumptions!$H$32/SUM(Assumptions!$C$32:$N$32) -> 500000 | W6: =Assumptions!$D$7*Assumptions!$I$32/SUM(Assumptions!$C$32:$N$32) -> 475000 | X6: =Assumptions!$D$7*Assumptions!$J$32/SUM(Assumptions!$C$32:$N$32) -> 450000 | Y6: =Assumptions!$D$7*Assumptions!$K$32/SUM(Assumptions!$C$32:$N$32) -> 500000 | Z6: =Assumptions!$D$7*Assumptions!$L$32/SUM(Assumptions!$C$32:$N$32) -> 525000 | AA6: =Assumptions!$D$7*Assumptions!$M$32/SUM(Assumptions!$C$32:$N$32) -> 650000 | AB6: =Assumptions!$D$7*Assumptions!$N$32/SUM(Assumptions!$C$32:$N$32) -> 675000
B9: COGS | C9: =SUM(D9:O9) -> 2687700 | D9: =D6*(1-Assumptions!$C$11) -> 190378.75 | E9: =E6*(1-Assumptions!$C$11) -> 190378.75 | F9: =F6*(1-Assumptions!$C$11) -> 201577.5 | G9: =G6*(1-Assumptions!$C$11) -> 201577.5 | H9: =H6*(1-Assumptions!$C$11) -> 212776.25 | I9: =I6*(1-Assumptions!$C$11) -> 223975 | J9: =J6*(1-Assumptions!$C$11) -> 212776.25 | K9: =K6*(1-Assumptions!$C$11) -> 201577.5 | ... O9: =O6*(1-Assumptions!$C$11) -> 302366.25 | P9: =SUM(Q9:AB9) -> 3162000 | Q9: =Q6*(1-Assumptions!$C$11) -> 223975 | R9: =R6*(1-Assumptions!$C$11) -> 223975 | S9: =S6*(1-Assumptions!$C$11) -> 237150 | T9: =T6*(1-Assumptions!$C$11) -> 237150 | U9: =U6*(1-Assumptions!$C$11) -> 250325 | V9: =V6*(1-Assumptions!$C$11) -> 263500 | W9: =W6*(1-Assumptions!$C$11) -> 250325 | X9: =X6*(1-Assumptions!$C$11) -> 237150 | ... AB9: =AB6*(1-Assumptions!$C$11) -> 355725
B11: Gross Profit | C11: =SUM(D11:O11) -> 2412300 | D11: =D6-D9 -> 170871.25 | E11: =E6-E9 -> 170871.25 | F11: =F6-F9 -> 180922.5 | G11: =G6-G9 -> 180922.5 | H11: =H6-H9 -> 190973.75 | I11: =I6-I9 -> 201025 | J11: =J6-J9 -> 190973.75 | K11: =K6-K9 -> 180922.5 | ... O11: =O6-O9 -> 271383.75 | P11: =SUM(Q11:AB11) -> 2838000 | Q11: =Q6-Q9 -> 201025 | R11: =R6-R9 -> 201025 | S11: =S6-S9 -> 212850 | T11: =T6-T9 -> 212850 | U11: =U6-U9 -> 224675 | V11: =V6-V9 -> 236500 | W11: =W6-W9 -> 224675 | X11: =X6-X9 -> 212850 | ... AB11: =AB6-AB9 -> 319275
B12: Gross Margin % | C12: =IF(C6=0,0,C11/C6) -> 0.473 | D12: =IF(D6=0,0,D11/D6) -> 0.473 | E12: =IF(E6=0,0,E11/E6) -> 0.473 | F12: =IF(F6=0,0,F11/F6) -> 0.473 | G12: =IF(G6=0,0,G11/G6) -> 0.473 | H12: =IF(H6=0,0,H11/H6) -> 0.473 | I12: =IF(I6=0,0,I11/I6) -> 0.473 | J12: =IF(J6=0,0,J11/J6) -> 0.473 | ... AB12: =IF(AB6=0,0,AB11/AB6) -> 0.473
B14: Operating Expenses
B15: Salaries & Benefits | C15: =SUM(D15:O15) -> 546250 | D15: =Headcount!$D$28*(1+Assumptions!$C$15)/12 -> 45520.833 | E15: =Headcount!$D$28*(1+Assumptions!$C$15)/12 -> 45520.833 | F15: =Headcount!$D$28*(1+Assumptions!$C$15)/12 -> 45520.833 | G15: =Headcount!$D$28*(1+Assumptions!$C$15)/12 -> 45520.833 | H15: =Headcount!$D$28*(1+Assumptions!$C$15)/12 -> 45520.833 | I15: =Headcount!$D$28*(1+Assumptions!$C$15)/12 -> 45520.833 | J15: =Headcount!$D$28*(1+Assumptions!$C$15)/12 -> 45520.833 | K15: =Headcount!$D$28*(1+Assumptions!$C$15)/12 -> 45520.833 | ... O15: =Headcount!$D$28*(1+Assumptions!$C$15)/12 -> 45520.833 | P15: =SUM(Q15:AB15) -> 565368.75 | Q15: =Headcount!$E$28*(1+Assumptions!$C$15)/12 -> 47114.062 | R15: =Headcount!$E$28*(1+Assumptions!$C$15)/12 -> 47114.062 | S15: =Headcount!$E$28*(1+Assumptions!$C$15)/12 -> 47114.062 | T15: =Headcount!$E$28*(1+Assumptions!$C$15)/12 -> 47114.062 | U15: =Headcount!$E$28*(1+Assumptions!$C$15)/12 -> 47114.062 | V15: =Headcount!$E$28*(1+Assumptions!$C$15)/12 -> 47114.062 | W15: =Headcount!$E$28*(1+Assumptions!$C$15)/12 -> 47114.062 | X15: =Headcount!$E$28*(1+Assumptions!$C$15)/12 -> 47114.062 | ... AB15: =Headcount!$E$28*(1+Assumptions!$C$15)/12 -> 47114.062
B16: Sales Commission | C16: =SUM(D16:O16) -> 102000 | D16: =D6*Assumptions!$C$16 -> 7225 | E16: =E6*Assumptions!$C$16 -> 7225 | F16: =F6*Assumptions!$C$16 -> 7650 | G16: =G6*Assumptions!$C$16 -> 7650 | H16: =H6*Assumptions!$C$16 -> 8075 | I16: =I6*Assumptions!$C$16 -> 8500 | J16: =J6*Assumptions!$C$16 -> 8075 | K16: =K6*Assumptions!$C$16 -> 7650 | ... O16: =O6*Assumptions!$C$16 -> 11475 | P16: =SUM(Q16:AB16) -> 120000 | Q16: =Q6*Assumptions!$C$16 -> 8500 | R16: =R6*Assumptions!$C$16 -> 8500 | S16: =S6*Assumptions!$C$16 -> 9000 | T16: =T6*Assumptions!$C$16 -> 9000 | U16: =U6*Assumptions!$C$16 -> 9500 | V16: =V6*Assumptions!$C$16 -> 10000 | W16: =W6*Assumptions!$C$16 -> 9500 | X16: =X6*Assumptions!$C$16 -> 9000 | ... AB16: =AB6*Assumptions!$C$16 -> 13500
B17: Rent & Facilities | C17: =SUM(D17:O17) -> 90000 | D17: =Assumptions!$D$23/12 -> 7500 | E17: =Assumptions!$D$23/12 -> 7500 | F17: =Assumptions!$D$23/12 -> 7500 | G17: =Assumptions!$D$23/12 -> 7500 | H17: =Assumptions!$D$23/12 -> 7500 | I17: =Assumptions!$D$23/12 -> 7500 | J17: =Assumptions!$D$23/12 -> 7500 | K17: =Assumptions!$D$23/12 -> 7500 | ... O17: =Assumptions!$D$23/12 -> 7500 | P17: =SUM(Q17:AB17) -> 93150 | Q17: =Assumptions!$D$23*(1+Assumptions!$C$17)/12 -> 7762.5 | R17: =Assumptions!$D$23*(1+Assumptions!$C$17)/12 -> 7762.5 | S17: =Assumptions!$D$23*(1+Assumptions!$C$17)/12 -> 7762.5 | T17: =Assumptions!$D$23*(1+Assumptions!$C$17)/12 -> 7762.5 | U17: =Assumptions!$D$23*(1+Assumptions!$C$17)/12 -> 7762.5 | V17: =Assumptions!$D$23*(1+Assumptions!$C$17)/12 -> 7762.5 | W17: =Assumptions!$D$23*(1+Assumptions!$C$17)/12 -> 7762.5 | X17: =Assumptions!$D$23*(1+Assumptions!$C$17)/12 -> 7762.5 | ... AB17: =Assumptions!$D$23*(1+Assumptions!$C$17)/12 -> 7762.5
B18: Travel | C18: =SUM(D18:O18) -> 140000 | D18: =Assumptions!$D$24/12 -> 11666.667 | E18: =Assumptions!$D$24/12 -> 11666.667 | F18: =Assumptions!$D$24/12 -> 11666.667 | G18: =Assumptions!$D$24/12 -> 11666.667 | H18: =Assumptions!$D$24/12 -> 11666.667 | I18: =Assumptions!$D$24/12 -> 11666.667 | J18: =Assumptions!$D$24/12 -> 11666.667 | K18: =Assumptions!$D$24/12 -> 11666.667 | ... O18: =Assumptions!$D$24/12 -> 11666.667 | P18: =SUM(Q18:AB18) -> 144900 | Q18: =Assumptions!$D$24*(1+Assumptions!$C$17)/12 -> 12075 | R18: =Assumptions!$D$24*(1+Assumptions!$C$17)/12 -> 12075 | S18: =Assumptions!$D$24*(1+Assumptions!$C$17)/12 -> 12075 | T18: =Assumptions!$D$24*(1+Assumptions!$C$17)/12 -> 12075 | U18: =Assumptions!$D$24*(1+Assumptions!$C$17)/12 -> 12075 | V18: =Assumptions!$D$24*(1+Assumptions!$C$17)/12 -> 12075 | W18: =Assumptions!$D$24*(1+Assumptions!$C$17)/12 -> 12075 | X18: =Assumptions!$D$24*(1+Assumptions!$C$17)/12 -> 12075 | ... AB18: =Assumptions!$D$24*(1+Assumptions!$C$17)/12 -> 12075
B19: Professional Services | C19: =SUM(D19:O19) -> 60000 | D19: =Assumptions!$D$25/12 -> 5000 | E19: =Assumptions!$D$25/12 -> 5000 | F19: =Assumptions!$D$25/12 -> 5000 | G19: =Assumptions!$D$25/12 -> 5000 | H19: =Assumptions!$D$25/12 -> 5000 | I19: =Assumptions!$D$25/12 -> 5000 | J19: =Assumptions!$D$25/12 -> 5000 | K19: =Assumptions!$D$25/12 -> 5000 | ... O19: =Assumptions!$D$25/12 -> 5000 | P19: =SUM(Q19:AB19) -> 62100 | Q19: =Assumptions!$D$25*(1+Assumptions!$C$17)/12 -> 5175 | R19: =Assumptions!$D$25*(1+Assumptions!$C$17)/12 -> 5175 | S19: =Assumptions!$D$25*(1+Assumptions!$C$17)/12 -> 5175 | T19: =Assumptions!$D$25*(1+Assumptions!$C$17)/12 -> 5175 | U19: =Assumptions!$D$25*(1+Assumptions!$C$17)/12 -> 5175 | V19: =Assumptions!$D$25*(1+Assumptions!$C$17)/12 -> 5175 | W19: =Assumptions!$D$25*(1+Assumptions!$C$17)/12 -> 5175 | X19: =Assumptions!$D$25*(1+Assumptions!$C$17)/12 -> 5175 | ... AB19: =Assumptions!$D$25*(1+Assumptions!$C$17)/12 -> 5175
B20: Marketing | C20: =SUM(D20:O20) -> 40000 | D20: =Assumptions!$D$26/12 -> 3333.3333 | E20: =Assumptions!$D$26/12 -> 3333.3333 | F20: =Assumptions!$D$26/12 -> 3333.3333 | G20: =Assumptions!$D$26/12 -> 3333.3333 | H20: =Assumptions!$D$26/12 -> 3333.3333 | I20: =Assumptions!$D$26/12 -> 3333.3333 | J20: =Assumptions!$D$26/12 -> 3333.3333 | K20: =Assumptions!$D$26/12 -> 3333.3333 | ... O20: =Assumptions!$D$26/12 -> 3333.3333 | P20: =SUM(Q20:AB20) -> 41400 | Q20: =Assumptions!$D$26*(1+Assumptions!$C$17)/12 -> 3450 | R20: =Assumptions!$D$26*(1+Assumptions!$C$17)/12 -> 3450 | S20: =Assumptions!$D$26*(1+Assumptions!$C$17)/12 -> 3450 | T20: =Assumptions!$D$26*(1+Assumptions!$C$17)/12 -> 3450 | U20: =Assumptions!$D$26*(1+Assumptions!$C$17)/12 -> 3450 | V20: =Assumptions!$D$26*(1+Assumptions!$C$17)/12 -> 3450 | W20: =Assumptions!$D$26*(1+Assumptions!$C$17)/12 -> 3450 | X20: =Assumptions!$D$26*(1+Assumptions!$C$17)/12 -> 3450 | ... AB20: =Assumptions!$D$26*(1+Assumptions!$C$17)/12 -> 3450
B21: Freight & Logistics | C21: =SUM(D21:O21) -> 160000 | D21: =Assumptions!$D$27/12 -> 13333.333 | E21: =Assumptions!$D$27/12 -> 13333.333 | F21: =Assumptions!$D$27/12 -> 13333.333 | G21: =Assumptions!$D$27/12 -> 13333.333 | H21: =Assumptions!$D$27/12 -> 13333.333 | I21: =Assumptions!$D$27/12 -> 13333.333 | J21: =Assumptions!$D$27/12 -> 13333.333 | K21: =Assumptions!$D$27/12 -> 13333.333 | ... O21: =Assumptions!$D$27/12 -> 13333.333 | P21: =SUM(Q21:AB21) -> 165600 | Q21: =Assumptions!$D$27*(1+Assumptions!$C$17)/12 -> 13800 | R21: =Assumptions!$D$27*(1+Assumptions!$C$17)/12 -> 13800 | S21: =Assumptions!$D$27*(1+Assumptions!$C$17)/12 -> 13800 | T21: =Assumptions!$D$27*(1+Assumptions!$C$17)/12 -> 13800 | U21: =Assumptions!$D$27*(1+Assumptions!$C$17)/12 -> 13800 | V21: =Assumptions!$D$27*(1+Assumptions!$C$17)/12 -> 13800 | W21: =Assumptions!$D$27*(1+Assumptions!$C$17)/12 -> 13800 | X21: =Assumptions!$D$27*(1+Assumptions!$C$17)/12 -> 13800 | ... AB21: =Assumptions!$D$27*(1+Assumptions!$C$17)/12 -> 13800
B22: G&A / Admin | C22: =SUM(D22:O22) -> 80000 | D22: =Assumptions!$D$28/12 -> 6666.6667 | E22: =Assumptions!$D$28/12 -> 6666.6667 | F22: =Assumptions!$D$28/12 -> 6666.6667 | G22: =Assumptions!$D$28/12 -> 6666.6667 | H22: =Assumptions!$D$28/12 -> 6666.6667 | I22: =Assumptions!$D$28/12 -> 6666.6667 | J22: =Assumptions!$D$28/12 -> 6666.6667 | K22: =Assumptions!$D$28/12 -> 6666.6667 | ... O22: =Assumptions!$D$28/12 -> 6666.6667 | P22: =SUM(Q22:AB22) -> 82800 | Q22: =Assumptions!$D$28*(1+Assumptions!$C$17)/12 -> 6900 | R22: =Assumptions!$D$28*(1+Assumptions!$C$17)/12 -> 6900 | S22: =Assumptions!$D$28*(1+Assumptions!$C$17)/12 -> 6900 | T22: =Assumptions!$D$28*(1+Assumptions!$C$17)/12 -> 6900 | U22: =Assumptions!$D$28*(1+Assumptions!$C$17)/12 -> 6900 | V22: =Assumptions!$D$28*(1+Assumptions!$C$17)/12 -> 6900 | W22: =Assumptions!$D$28*(1+Assumptions!$C$17)/12 -> 6900 | X22: =Assumptions!$D$28*(1+Assumptions!$C$17)/12 -> 6900 | ... AB22: =Assumptions!$D$28*(1+Assumptions!$C$17)/12 -> 6900
B23: Total Operating Expenses | C23: =SUM(D23:O23) -> 1218250 | D23: =SUM(D15:D22) -> 100245.83 | E23: =SUM(E15:E22) -> 100245.83 | F23: =SUM(F15:F22) -> 100670.83 | G23: =SUM(G15:G22) -> 100670.83 | H23: =SUM(H15:H22) -> 101095.83 | I23: =SUM(I15:I22) -> 101520.83 | J23: =SUM(J15:J22) -> 101095.83 | K23: =SUM(K15:K22) -> 100670.83 | ... O23: =SUM(O15:O22) -> 104495.83 | P23: =SUM(Q23:AB23) -> 1275318.8 | Q23: =SUM(Q15:Q22) -> 104776.56 | R23: =SUM(R15:R22) -> 104776.56 | S23: =SUM(S15:S22) -> 105276.56 | T23: =SUM(T15:T22) -> 105276.56 | U23: =SUM(U15:U22) -> 105776.56 | V23: =SUM(V15:V22) -> 106276.56 | W23: =SUM(W15:W22) -> 105776.56 | X23: =SUM(X15:X22) -> 105276.56 | ... AB23: =SUM(AB15:AB22) -> 109776.56
B25: EBITDA | C25: =SUM(D25:O25) -> 1194050 | D25: =D11-D23 -> 70625.417 | E25: =E11-E23 -> 70625.417 | F25: =F11-F23 -> 80251.667 | G25: =G11-G23 -> 80251.667 | H25: =H11-H23 -> 89877.917 | I25: =I11-I23 -> 99504.167 | J25: =J11-J23 -> 89877.917 | K25: =K11-K23 -> 80251.667 | ... O25: =O11-O23 -> 166887.92 | P25: =SUM(Q25:AB25) -> 1562681.2 | Q25: =Q11-Q23 -> 96248.438 | R25: =R11-R23 -> 96248.438 | S25: =S11-S23 -> 107573.44 | T25: =T11-T23 -> 107573.44 | U25: =U11-U23 -> 118898.44 | V25: =V11-V23 -> 130223.44 | W25: =W11-W23 -> 118898.44 | X25: =X11-X23 -> 107573.44 | ... AB25: =AB11-AB23 -> 209498.44
B26: EBITDA Margin % | C26: =IF(C6=0,0,C25/C6) -> 0.23412745 | D26: =IF(D6=0,0,D25/D6) -> 0.19550288 | E26: =IF(E6=0,0,E25/E6) -> 0.19550288 | F26: =IF(F6=0,0,F25/F6) -> 0.20980828 | G26: =IF(G6=0,0,G25/G6) -> 0.20980828 | H26: =IF(H6=0,0,H25/H6) -> 0.22260784 | I26: =IF(I6=0,0,I25/I6) -> 0.23412745 | J26: =IF(J6=0,0,J25/J6) -> 0.22260784 | ... AB26: =IF(AB6=0,0,AB25/AB6) -> 0.31036806
B28: Depreciation & Amortization | C28: =SUM(D28:O28) -> 20000 | D28: =Assumptions!$C$19/12 -> 1666.6667 | E28: =Assumptions!$C$19/12 -> 1666.6667 | F28: =Assumptions!$C$19/12 -> 1666.6667 | G28: =Assumptions!$C$19/12 -> 1666.6667 | H28: =Assumptions!$C$19/12 -> 1666.6667 | I28: =Assumptions!$C$19/12 -> 1666.6667 | J28: =Assumptions!$C$19/12 -> 1666.6667 | K28: =Assumptions!$C$19/12 -> 1666.6667 | ... O28: =Assumptions!$C$19/12 -> 1666.6667 | P28: =SUM(Q28:AB28) -> 20000 | Q28: =Assumptions!$C$19/12 -> 1666.6667 | R28: =Assumptions!$C$19/12 -> 1666.6667 | S28: =Assumptions!$C$19/12 -> 1666.6667 | T28: =Assumptions!$C$19/12 -> 1666.6667 | U28: =Assumptions!$C$19/12 -> 1666.6667 | V28: =Assumptions!$C$19/12 -> 1666.6667 | W28: =Assumptions!$C$19/12 -> 1666.6667 | X28: =Assumptions!$C$19/12 -> 1666.6667 | ... AB28: =Assumptions!$C$19/12 -> 1666.6667
B30: EBIT | C30: =SUM(D30:O30) -> 1174050 | D30: =D25-D28 -> 68958.75 | E30: =E25-E28 -> 68958.75 | F30: =F25-F28 -> 78585 | G30: =G25-G28 -> 78585 | H30: =H25-H28 -> 88211.25 | I30: =I25-I28 -> 97837.5 | J30: =J25-J28 -> 88211.25 | K30: =K25-K28 -> 78585 | ... O30: =O25-O28 -> 165221.25 | P30: =SUM(Q30:AB30) -> 1542681.2 | Q30: =Q25-Q28 -> 94581.771 | R30: =R25-R28 -> 94581.771 | S30: =S25-S28 -> 105906.77 | T30: =T25-T28 -> 105906.77 | U30: =U25-U28 -> 117231.77 | V30: =V25-V28 -> 128556.77 | W30: =W25-W28 -> 117231.77 | X30: =X25-X28 -> 105906.77 | ... AB30: =AB25-AB28 -> 207831.77
B31: EBIT Margin % | C31: =IF(C6=0,0,C30/C6) -> 0.23020588 | D31: =IF(D6=0,0,D30/D6) -> 0.19088927 | E31: =IF(E6=0,0,E30/E6) -> 0.19088927 | F31: =IF(F6=0,0,F30/F6) -> 0.20545098 | G31: =IF(G6=0,0,G30/G6) -> 0.20545098 | H31: =IF(H6=0,0,H30/H6) -> 0.21847988 | I31: =IF(I6=0,0,I30/I6) -> 0.23020588 | J31: =IF(J6=0,0,J30/J6) -> 0.21847988 | ... AB31: =IF(AB6=0,0,AB30/AB6) -> 0.30789892

Sheet Consolidated PL
B1: Lumin Light — Consolidated P&L (USA + Nigeria)
B2: No intercompany elimination line — both subsidiaries buy at the same price from an external supplier, so Consolidated is a straight sum. | C2: FY2025 | P2: FY2026
C3: Annual | D3: Jan | E3: Feb | F3: Mar | G3: Apr | H3: May | I3: Jun | J3: Jul | K3: Aug | L3: Sep | M3: Oct | N3: Nov | O3: Dec | P3: Annual | Q3: Jan | R3: Feb | S3: Mar | T3: Apr | U3: May | V3: Jun | W3: Jul | X3: Aug | Y3: Sep | Z3: Oct | AA3: Nov | AB3: Dec
B6: Revenue | C6: ='USA PL'!C6+'Nigeria PL'!C6 -> 12950000 | D6: ='USA PL'!D6+'Nigeria PL'!D6 -> 917291.67 | E6: ='USA PL'!E6+'Nigeria PL'!E6 -> 917291.67 | F6: ='USA PL'!F6+'Nigeria PL'!F6 -> 971250 | G6: ='USA PL'!G6+'Nigeria PL'!G6 -> 971250 | H6: ='USA PL'!H6+'Nigeria PL'!H6 -> 1025208.3 | I6: ='USA PL'!I6+'Nigeria PL'!I6 -> 1079166.7 | J6: ='USA PL'!J6+'Nigeria PL'!J6 -> 1025208.3 | ... AB6: ='USA PL'!AB6+'Nigeria PL'!AB6 -> 1687500
B9: COGS | C9: ='USA PL'!C9+'Nigeria PL'!C9 -> 6824650 | D9: ='USA PL'!D9+'Nigeria PL'!D9 -> 483412.71 | E9: ='USA PL'!E9+'Nigeria PL'!E9 -> 483412.71 | F9: ='USA PL'!F9+'Nigeria PL'!F9 -> 511848.75 | G9: ='USA PL'!G9+'Nigeria PL'!G9 -> 511848.75 | H9: ='USA PL'!H9+'Nigeria PL'!H9 -> 540284.79 | I9: ='USA PL'!I9+'Nigeria PL'!I9 -> 568720.83 | J9: ='USA PL'!J9+'Nigeria PL'!J9 -> 540284.79 | ... AB9: ='USA PL'!AB9+'Nigeria PL'!AB9 -> 889312.5
B11: Gross Profit | C11: ='USA PL'!C11+'Nigeria PL'!C11 -> 6125350 | D11: ='USA PL'!D11+'Nigeria PL'!D11 -> 433878.96 | E11: ='USA PL'!E11+'Nigeria PL'!E11 -> 433878.96 | F11: ='USA PL'!F11+'Nigeria PL'!F11 -> 459401.25 | G11: ='USA PL'!G11+'Nigeria PL'!G11 -> 459401.25 | H11: ='USA PL'!H11+'Nigeria PL'!H11 -> 484923.54 | I11: ='USA PL'!I11+'Nigeria PL'!I11 -> 510445.83 | J11: ='USA PL'!J11+'Nigeria PL'!J11 -> 484923.54 | ... AB11: ='USA PL'!AB11+'Nigeria PL'!AB11 -> 798187.5
B12: Gross Margin % | C12: =IF(C6=0,0,C11/C6) -> 0.473 | D12: =IF(D6=0,0,D11/D6) -> 0.473 | E12: =IF(E6=0,0,E11/E6) -> 0.473 | F12: =IF(F6=0,0,F11/F6) -> 0.473 | G12: =IF(G6=0,0,G11/G6) -> 0.473 | H12: =IF(H6=0,0,H11/H6) -> 0.473 | I12: =IF(I6=0,0,I11/I6) -> 0.473 | J12: =IF(J6=0,0,J11/J6) -> 0.473 | ... AB12: =IF(AB6=0,0,AB11/AB6) -> 0.473
B14: Operating Expenses
B15: Salaries & Benefits | C15: ='USA PL'!C15+'Nigeria PL'!C15 -> 2652500 | D15: ='USA PL'!D15+'Nigeria PL'!D15 -> 221041.67 | E15: ='USA PL'!E15+'Nigeria PL'!E15 -> 221041.67 | F15: ='USA PL'!F15+'Nigeria PL'!F15 -> 221041.67 | G15: ='USA PL'!G15+'Nigeria PL'!G15 -> 221041.67 | H15: ='USA PL'!H15+'Nigeria PL'!H15 -> 221041.67 | I15: ='USA PL'!I15+'Nigeria PL'!I15 -> 221041.67 | J15: ='USA PL'!J15+'Nigeria PL'!J15 -> 221041.67 | ... AB15: ='USA PL'!AB15+'Nigeria PL'!AB15 -> 228778.12
B16: Sales Commission | C16: ='USA PL'!C16+'Nigeria PL'!C16 -> 259000 | D16: ='USA PL'!D16+'Nigeria PL'!D16 -> 18345.833 | E16: ='USA PL'!E16+'Nigeria PL'!E16 -> 18345.833 | F16: ='USA PL'!F16+'Nigeria PL'!F16 -> 19425 | G16: ='USA PL'!G16+'Nigeria PL'!G16 -> 19425 | H16: ='USA PL'!H16+'Nigeria PL'!H16 -> 20504.167 | I16: ='USA PL'!I16+'Nigeria PL'!I16 -> 21583.333 | J16: ='USA PL'!J16+'Nigeria PL'!J16 -> 20504.167 | ... AB16: ='USA PL'!AB16+'Nigeria PL'!AB16 -> 33750
B17: Rent & Facilities | C17: ='USA PL'!C17+'Nigeria PL'!C17 -> 240000 | D17: ='USA PL'!D17+'Nigeria PL'!D17 -> 20000 | E17: ='USA PL'!E17+'Nigeria PL'!E17 -> 20000 | F17: ='USA PL'!F17+'Nigeria PL'!F17 -> 20000 | G17: ='USA PL'!G17+'Nigeria PL'!G17 -> 20000 | H17: ='USA PL'!H17+'Nigeria PL'!H17 -> 20000 | I17: ='USA PL'!I17+'Nigeria PL'!I17 -> 20000 | J17: ='USA PL'!J17+'Nigeria PL'!J17 -> 20000 | ... AB17: ='USA PL'!AB17+'Nigeria PL'!AB17 -> 20700
B18: Travel | C18: ='USA PL'!C18+'Nigeria PL'!C18 -> 370000 | D18: ='USA PL'!D18+'Nigeria PL'!D18 -> 30833.333 | E18: ='USA PL'!E18+'Nigeria PL'!E18 -> 30833.333 | F18: ='USA PL'!F18+'Nigeria PL'!F18 -> 30833.333 | G18: ='USA PL'!G18+'Nigeria PL'!G18 -> 30833.333 | H18: ='USA PL'!H18+'Nigeria PL'!H18 -> 30833.333 | I18: ='USA PL'!I18+'Nigeria PL'!I18 -> 30833.333 | J18: ='USA PL'!J18+'Nigeria PL'!J18 -> 30833.333 | ... AB18: ='USA PL'!AB18+'Nigeria PL'!AB18 -> 31912.5
B19: Professional Services | C19: ='USA PL'!C19+'Nigeria PL'!C19 -> 200000 | D19: ='USA PL'!D19+'Nigeria PL'!D19 -> 16666.667 | E19: ='USA PL'!E19+'Nigeria PL'!E19 -> 16666.667 | F19: ='USA PL'!F19+'Nigeria PL'!F19 -> 16666.667 | G19: ='USA PL'!G19+'Nigeria PL'!G19 -> 16666.667 | H19: ='USA PL'!H19+'Nigeria PL'!H19 -> 16666.667 | I19: ='USA PL'!I19+'Nigeria PL'!I19 -> 16666.667 | J19: ='USA PL'!J19+'Nigeria PL'!J19 -> 16666.667 | ... AB19: ='USA PL'!AB19+'Nigeria PL'!AB19 -> 17250
B20: Marketing | C20: ='USA PL'!C20+'Nigeria PL'!C20 -> 130000 | D20: ='USA PL'!D20+'Nigeria PL'!D20 -> 10833.333 | E20: ='USA PL'!E20+'Nigeria PL'!E20 -> 10833.333 | F20: ='USA PL'!F20+'Nigeria PL'!F20 -> 10833.333 | G20: ='USA PL'!G20+'Nigeria PL'!G20 -> 10833.333 | H20: ='USA PL'!H20+'Nigeria PL'!H20 -> 10833.333 | I20: ='USA PL'!I20+'Nigeria PL'!I20 -> 10833.333 | J20: ='USA PL'!J20+'Nigeria PL'!J20 -> 10833.333 | ... AB20: ='USA PL'!AB20+'Nigeria PL'!AB20 -> 11212.5
B21: Freight & Logistics | C21: ='USA PL'!C21+'Nigeria PL'!C21 -> 340000 | D21: ='USA PL'!D21+'Nigeria PL'!D21 -> 28333.333 | E21: ='USA PL'!E21+'Nigeria PL'!E21 -> 28333.333 | F21: ='USA PL'!F21+'Nigeria PL'!F21 -> 28333.333 | G21: ='USA PL'!G21+'Nigeria PL'!G21 -> 28333.333 | H21: ='USA PL'!H21+'Nigeria PL'!H21 -> 28333.333 | I21: ='USA PL'!I21+'Nigeria PL'!I21 -> 28333.333 | J21: ='USA PL'!J21+'Nigeria PL'!J21 -> 28333.333 | ... AB21: ='USA PL'!AB21+'Nigeria PL'!AB21 -> 29325
B22: G&A / Admin | C22: ='USA PL'!C22+'Nigeria PL'!C22 -> 220000 | D22: ='USA PL'!D22+'Nigeria PL'!D22 -> 18333.333 | E22: ='USA PL'!E22+'Nigeria PL'!E22 -> 18333.333 | F22: ='USA PL'!F22+'Nigeria PL'!F22 -> 18333.333 | G22: ='USA PL'!G22+'Nigeria PL'!G22 -> 18333.333 | H22: ='USA PL'!H22+'Nigeria PL'!H22 -> 18333.333 | I22: ='USA PL'!I22+'Nigeria PL'!I22 -> 18333.333 | J22: ='USA PL'!J22+'Nigeria PL'!J22 -> 18333.333 | ... AB22: ='USA PL'!AB22+'Nigeria PL'!AB22 -> 18975
B23: Total Operating Expenses | C23: ='USA PL'!C23+'Nigeria PL'!C23 -> 4411500 | D23: ='USA PL'!D23+'Nigeria PL'!D23 -> 364387.5 | E23: ='USA PL'!E23+'Nigeria PL'!E23 -> 364387.5 | F23: ='USA PL'!F23+'Nigeria PL'!F23 -> 365466.67 | G23: ='USA PL'!G23+'Nigeria PL'!G23 -> 365466.67 | H23: ='USA PL'!H23+'Nigeria PL'!H23 -> 366545.83 | I23: ='USA PL'!I23+'Nigeria PL'!I23 -> 367625 | J23: ='USA PL'!J23+'Nigeria PL'!J23 -> 366545.83 | ... AB23: ='USA PL'!AB23+'Nigeria PL'!AB23 -> 391903.12
B25: EBITDA | C25: ='USA PL'!C25+'Nigeria PL'!C25 -> 1713850 | D25: ='USA PL'!D25+'Nigeria PL'!D25 -> 69491.458 | E25: ='USA PL'!E25+'Nigeria PL'!E25 -> 69491.458 | F25: ='USA PL'!F25+'Nigeria PL'!F25 -> 93934.583 | G25: ='USA PL'!G25+'Nigeria PL'!G25 -> 93934.583 | H25: ='USA PL'!H25+'Nigeria PL'!H25 -> 118377.71 | I25: ='USA PL'!I25+'Nigeria PL'!I25 -> 142820.83 | J25: ='USA PL'!J25+'Nigeria PL'!J25 -> 118377.71 | ... AB25: ='USA PL'!AB25+'Nigeria PL'!AB25 -> 406284.38
B26: EBITDA Margin % | C26: =IF(C6=0,0,C25/C6) -> 0.13234363 | D26: =IF(D6=0,0,D25/D6) -> 0.075757211 | E26: =IF(E6=0,0,E25/E6) -> 0.075757211 | F26: =IF(F6=0,0,F25/F6) -> 0.096715144 | G26: =IF(G6=0,0,G25/G6) -> 0.096715144 | H26: =IF(H6=0,0,H25/H6) -> 0.11546698 | I26: =IF(I6=0,0,I25/I6) -> 0.13234363 | J26: =IF(J6=0,0,J25/J6) -> 0.11546698 | ... AB26: =IF(AB6=0,0,AB25/AB6) -> 0.24076111
B28: Depreciation & Amortization | C28: ='USA PL'!C28+'Nigeria PL'!C28 -> 60000 | D28: ='USA PL'!D28+'Nigeria PL'!D28 -> 5000 | E28: ='USA PL'!E28+'Nigeria PL'!E28 -> 5000 | F28: ='USA PL'!F28+'Nigeria PL'!F28 -> 5000 | G28: ='USA PL'!G28+'Nigeria PL'!G28 -> 5000 | H28: ='USA PL'!H28+'Nigeria PL'!H28 -> 5000 | I28: ='USA PL'!I28+'Nigeria PL'!I28 -> 5000 | J28: ='USA PL'!J28+'Nigeria PL'!J28 -> 5000 | ... AB28: ='USA PL'!AB28+'Nigeria PL'!AB28 -> 5000
B30: EBIT | C30: ='USA PL'!C30+'Nigeria PL'!C30 -> 1653850 | D30: ='USA PL'!D30+'Nigeria PL'!D30 -> 64491.458 | E30: ='USA PL'!E30+'Nigeria PL'!E30 -> 64491.458 | F30: ='USA PL'!F30+'Nigeria PL'!F30 -> 88934.583 | G30: ='USA PL'!G30+'Nigeria PL'!G30 -> 88934.583 | H30: ='USA PL'!H30+'Nigeria PL'!H30 -> 113377.71 | I30: ='USA PL'!I30+'Nigeria PL'!I30 -> 137820.83 | J30: ='USA PL'!J30+'Nigeria PL'!J30 -> 113377.71 | ... AB30: ='USA PL'!AB30+'Nigeria PL'!AB30 -> 401284.38
B31: EBIT Margin % | C31: =IF(C6=0,0,C30/C6) -> 0.12771042 | D31: =IF(D6=0,0,D30/D6) -> 0.070306382 | E31: =IF(E6=0,0,E30/E6) -> 0.070306382 | F31: =IF(F6=0,0,F30/F6) -> 0.091567139 | G31: =IF(G6=0,0,G30/G6) -> 0.091567139 | H31: =IF(H6=0,0,H30/H6) -> 0.11058992 | I31: =IF(I6=0,0,I30/I6) -> 0.12771042 | J31: =IF(J6=0,0,J30/J6) -> 0.11058992 | ... AB31: =IF(AB6=0,0,AB30/AB6) -> 0.23779815

Sheet Cash Flow
B1: Lumin Light — Cash Flow
B2: 1-month AR collection lag on Revenue (institutional buyers pay slowly); COGS and Opex paid same month — same logic as the Python actuals model.
C4: Jan-25 | D4: Feb-25 | E4: Mar-25 | F4: Apr-25 | G4: May-25 | H4: Jun-25 | I4: Jul-25 | J4: Aug-25 | K4: Sep-25 | L4: Oct-25 | M4: Nov-25 | N4: Dec-25 | O4: Jan-26 | P4: Feb-26 | Q4: Mar-26 | R4: Apr-26 | S4: May-26 | T4: Jun-26 | U4: Jul-26 | V4: Aug-26 | W4: Sep-26 | X4: Oct-26 | Y4: Nov-26 | Z4: Dec-26
B5: Lumin Light USA
B6: Opening Balance | C6: =Assumptions!$C$38 -> 2200000 | D6: =C11 -> 2198866 | E6: =D11 -> 2197732.1 | F6: =E11 -> 2178706.7 | G6: =F11 -> 2192389.6 | H6: =G11 -> 2188181 | I6: =H11 -> 2198789.4 | J6: =I11 -> 2259997.5 | K6: =J11 -> 2306388.8 | ... Z6: =Y11 -> 3038537
B7: Revenue Collected | C7: ='USA PL'!D6 -> 556041.67 | D7: ='USA PL'!D6 -> 556041.67 | E7: ='USA PL'!E6 -> 556041.67 | F7: ='USA PL'!F6 -> 588750 | G7: ='USA PL'!G6 -> 588750 | H7: ='USA PL'!H6 -> 621458.33 | I7: ='USA PL'!I6 -> 654166.67 | J7: ='USA PL'!J6 -> 621458.33 | K7: ='USA PL'!K6 -> 588750 | ... O7: ='USA PL'!O6 -> 883125 | P7: ='USA PL'!Q6 -> 637500 | Q7: ='USA PL'!R6 -> 637500 | R7: ='USA PL'!S6 -> 675000 | S7: ='USA PL'!T6 -> 675000 | T7: ='USA PL'!U6 -> 712500 | U7: ='USA PL'!V6 -> 750000 | V7: ='USA PL'!W6 -> 712500 | W7: ='USA PL'!X6 -> 675000 | ... Z7: ='USA PL'!AA6 -> 975000
B8: COGS Paid | C8: ='USA PL'!D9 -> 293033.96 | D8: ='USA PL'!E9 -> 293033.96 | E8: ='USA PL'!F9 -> 310271.25 | F8: ='USA PL'!G9 -> 310271.25 | G8: ='USA PL'!H9 -> 327508.54 | H8: ='USA PL'!I9 -> 344745.83 | I8: ='USA PL'!J9 -> 327508.54 | J8: ='USA PL'!K9 -> 310271.25 | ... N8: ='USA PL'!O9 -> 465406.88 | O8: ='USA PL'!Q9 -> 335962.5 | P8: ='USA PL'!R9 -> 335962.5 | Q8: ='USA PL'!S9 -> 355725 | R8: ='USA PL'!T9 -> 355725 | S8: ='USA PL'!U9 -> 375487.5 | T8: ='USA PL'!V9 -> 395250 | U8: ='USA PL'!W9 -> 375487.5 | V8: ='USA PL'!X9 -> 355725 | ... Z8: ='USA PL'!AB9 -> 533587.5
B9: Opex Paid | C9: ='USA PL'!D23 -> 264141.67 | D9: ='USA PL'!E23 -> 264141.67 | E9: ='USA PL'!F23 -> 264795.83 | F9: ='USA PL'!G23 -> 264795.83 | G9: ='USA PL'!H23 -> 265450 | H9: ='USA PL'!I23 -> 266104.17 | I9: ='USA PL'!J23 -> 265450 | J9: ='USA PL'!K23 -> 264795.83 | ... N9: ='USA PL'!O23 -> 270683.33 | O9: ='USA PL'!Q23 -> 274626.56 | P9: ='USA PL'!R23 -> 274626.56 | Q9: ='USA PL'!S23 -> 275376.56 | R9: ='USA PL'!T23 -> 275376.56 | S9: ='USA PL'!U23 -> 276126.56 | T9: ='USA PL'!V23 -> 276876.56 | U9: ='USA PL'!W23 -> 276126.56 | V9: ='USA PL'!X23 -> 275376.56 | ... Z9: ='USA PL'!AB23 -> 282126.56
B10: Net Cash Change | C10: =C7-C8-C9 -> -1133.9583 | D10: =D7-D8-D9 -> -1133.9583 | E10: =E7-E8-E9 -> -19025.417 | F10: =F7-F8-F9 -> 13682.917 | G10: =G7-G8-G9 -> -4208.5417 | H10: =H7-H8-H9 -> 10608.333 | I10: =I7-I8-I9 -> 61208.125 | J10: =J7-J8-J9 -> 46391.25 | ... Z10: =Z7-Z8-Z9 -> 159285.94
B11: Closing Balance | C11: =C6+C10 -> 2198866 | D11: =D6+D10 -> 2197732.1 | E11: =E6+E10 -> 2178706.7 | F11: =F6+F10 -> 2192389.6 | G11: =G6+G10 -> 2188181 | H11: =H6+H10 -> 2198789.4 | I11: =I6+I10 -> 2259997.5 | J11: =J6+J10 -> 2306388.8 | ... Z11: =Z6+Z10 -> 3197822.9
B13: Lumin Light Nigeria
B14: Opening Balance | C14: =Assumptions!$C$39 -> 2200000 | D14: =C19 -> 2270625.4 | E14: =D19 -> 2341250.8 | F14: =E19 -> 2400252.5 | G14: =F19 -> 2480504.2 | H14: =G19 -> 2549132.1 | I14: =H19 -> 2627386.2 | J14: =I19 -> 2738514.2 | K14: =J19 -> 2840015.8 | ... Z14: =Y19 -> 4458482.8
B15: Revenue Collected | C15: ='Nigeria PL'!D6 -> 361250 | D15: ='Nigeria PL'!D6 -> 361250 | E15: ='Nigeria PL'!E6 -> 361250 | F15: ='Nigeria PL'!F6 -> 382500 | G15: ='Nigeria PL'!G6 -> 382500 | H15: ='Nigeria PL'!H6 -> 403750 | I15: ='Nigeria PL'!I6 -> 425000 | J15: ='Nigeria PL'!J6 -> 403750 | K15: ='Nigeria PL'!K6 -> 382500 | ... O15: ='Nigeria PL'!O6 -> 573750 | P15: ='Nigeria PL'!Q6 -> 425000 | Q15: ='Nigeria PL'!R6 -> 425000 | R15: ='Nigeria PL'!S6 -> 450000 | S15: ='Nigeria PL'!T6 -> 450000 | T15: ='Nigeria PL'!U6 -> 475000 | U15: ='Nigeria PL'!V6 -> 500000 | V15: ='Nigeria PL'!W6 -> 475000 | W15: ='Nigeria PL'!X6 -> 450000 | ... Z15: ='Nigeria PL'!AA6 -> 650000
B16: COGS Paid | C16: ='Nigeria PL'!D9 -> 190378.75 | D16: ='Nigeria PL'!E9 -> 190378.75 | E16: ='Nigeria PL'!F9 -> 201577.5 | F16: ='Nigeria PL'!G9 -> 201577.5 | G16: ='Nigeria PL'!H9 -> 212776.25 | H16: ='Nigeria PL'!I9 -> 223975 | I16: ='Nigeria PL'!J9 -> 212776.25 | J16: ='Nigeria PL'!K9 -> 201577.5 | ... N16: ='Nigeria PL'!O9 -> 302366.25 | O16: ='Nigeria PL'!Q9 -> 223975 | P16: ='Nigeria PL'!R9 -> 223975 | Q16: ='Nigeria PL'!S9 -> 237150 | R16: ='Nigeria PL'!T9 -> 237150 | S16: ='Nigeria PL'!U9 -> 250325 | T16: ='Nigeria PL'!V9 -> 263500 | U16: ='Nigeria PL'!W9 -> 250325 | V16: ='Nigeria PL'!X9 -> 237150 | ... Z16: ='Nigeria PL'!AB9 -> 355725
B17: Opex Paid | C17: ='Nigeria PL'!D23 -> 100245.83 | D17: ='Nigeria PL'!E23 -> 100245.83 | E17: ='Nigeria PL'!F23 -> 100670.83 | F17: ='Nigeria PL'!G23 -> 100670.83 | G17: ='Nigeria PL'!H23 -> 101095.83 | H17: ='Nigeria PL'!I23 -> 101520.83 | I17: ='Nigeria PL'!J23 -> 101095.83 | J17: ='Nigeria PL'!K23 -> 100670.83 | ... N17: ='Nigeria PL'!O23 -> 104495.83 | O17: ='Nigeria PL'!Q23 -> 104776.56 | P17: ='Nigeria PL'!R23 -> 104776.56 | Q17: ='Nigeria PL'!S23 -> 105276.56 | R17: ='Nigeria PL'!T23 -> 105276.56 | S17: ='Nigeria PL'!U23 -> 105776.56 | T17: ='Nigeria PL'!V23 -> 106276.56 | U17: ='Nigeria PL'!W23 -> 105776.56 | V17: ='Nigeria PL'!X23 -> 105276.56 | ... Z17: ='Nigeria PL'!AB23 -> 109776.56
B18: Net Cash Change | C18: =C15-C16-C17 -> 70625.417 | D18: =D15-D16-D17 -> 70625.417 | E18: =E15-E16-E17 -> 59001.667 | F18: =F15-F16-F17 -> 80251.667 | G18: =G15-G16-G17 -> 68627.917 | H18: =H15-H16-H17 -> 78254.167 | I18: =I15-I16-I17 -> 111127.92 | J18: =J15-J16-J17 -> 101501.67 | ... Z18: =Z15-Z16-Z17 -> 184498.44
B19: Closing Balance | C19: =C14+C18 -> 2270625.4 | D19: =D14+D18 -> 2341250.8 | E19: =E14+E18 -> 2400252.5 | F19: =F14+F18 -> 2480504.2 | G19: =G14+G18 -> 2549132.1 | H19: =H14+H18 -> 2627386.2 | I19: =I14+I18 -> 2738514.2 | J19: =J14+J18 -> 2840015.8 | ... Z19: =Z14+Z18 -> 4642981.2
B21: Consolidated
B22: Opening Balance | C22: =C6+C14 -> 4400000 | D22: =D6+D14 -> 4469491.5 | E22: =E6+E14 -> 4538982.9 | F22: =F6+F14 -> 4578959.2 | G22: =G6+G14 -> 4672893.8 | H22: =H6+H14 -> 4737313.1 | I22: =I6+I14 -> 4826175.6 | J22: =J6+J14 -> 4998511.7 | ... Z22: =Z6+Z14 -> 7497019.8
B23: Revenue Collected | C23: =C7+C15 -> 917291.67 | D23: =D7+D15 -> 917291.67 | E23: =E7+E15 -> 917291.67 | F23: =F7+F15 -> 971250 | G23: =G7+G15 -> 971250 | H23: =H7+H15 -> 1025208.3 | I23: =I7+I15 -> 1079166.7 | J23: =J7+J15 -> 1025208.3 | ... Z23: =Z7+Z15 -> 1625000
B24: COGS Paid | C24: =C8+C16 -> 483412.71 | D24: =D8+D16 -> 483412.71 | E24: =E8+E16 -> 511848.75 | F24: =F8+F16 -> 511848.75 | G24: =G8+G16 -> 540284.79 | H24: =H8+H16 -> 568720.83 | I24: =I8+I16 -> 540284.79 | J24: =J8+J16 -> 511848.75 | ... Z24: =Z8+Z16 -> 889312.5
B25: Opex Paid | C25: =C9+C17 -> 364387.5 | D25: =D9+D17 -> 364387.5 | E25: =E9+E17 -> 365466.67 | F25: =F9+F17 -> 365466.67 | G25: =G9+G17 -> 366545.83 | H25: =H9+H17 -> 367625 | I25: =I9+I17 -> 366545.83 | J25: =J9+J17 -> 365466.67 | ... Z25: =Z9+Z17 -> 391903.12
B26: Net Cash Change | C26: =C10+C18 -> 69491.458 | D26: =D10+D18 -> 69491.458 | E26: =E10+E18 -> 39976.25 | F26: =F10+F18 -> 93934.583 | G26: =G10+G18 -> 64419.375 | H26: =H10+H18 -> 88862.5 | I26: =I10+I18 -> 172336.04 | J26: =J10+J18 -> 147892.92 | ... Z26: =Z10+Z18 -> 343784.38
B27: Closing Balance | C27: =C11+C19 -> 4469491.5 | D27: =D11+D19 -> 4538982.9 | E27: =E11+E19 -> 4578959.2 | F27: =F11+F19 -> 4672893.8 | G27: =G11+G19 -> 4737313.1 | H27: =H11+H19 -> 4826175.6 | I27: =I11+I19 -> 4998511.7 | J27: =J11+J19 -> 5146404.6 | ... Z27: =Z11+Z19 -> 7840804.2
